djangoldp_dashboard/__init__.py
djangoldp_dashboard/admin.py
djangoldp_dashboard/apps.py
djangoldp_dashboard/models.py
djangoldp_dashboard/fixtures/sample.json
djangoldp_dashboard/migrations/0001_initial.py
djangoldp_dashboard/migrations/0002_auto_20200330_1531.py
djangoldp_dashboard/migrations/0003_auto_20200522_1516.py
djangoldp_dashboard/migrations/0004_auto_20200610_1323.py
djangoldp_dashboard/migrations/0005_auto_20200619_1102.py
djangoldp_dashboard/migrations/0006_auto_20210219_1255.py
djangoldp_dashboard/migrations/0007_auto_20210223_2254.py
djangoldp_dashboard/migrations/0008_alter_dashboard_options_alter_dashboard_urlid.py
djangoldp_dashboard/migrations/0009_alter_dashboard_size.py
djangoldp_dashboard/migrations/0010_alter_dashboard_options.py
djangoldp_dashboard/migrations/0011_dashboard_order.py
djangoldp_dashboard/migrations/__init__.py
djangoldp_dashboard-3.0.3.dist-info/LICENSE
djangoldp_dashboard-3.0.3.dist-info/METADATA
djangoldp_dashboard-3.0.3.dist-info/WHEEL
djangoldp_dashboard-3.0.3.dist-info/top_level.txt
djangoldp_dashboard-3.0.3.dist-info/RECORD
