Metadata-Version: 2.1
Name: djangoldp-dashboard
Version: 3.0.3
Summary: djangoldp dashboard package
Home-page: http://git.startinblox.com/djangoldp_dashboard
License: MIT
Classifier: Programming Language :: Python :: 3
License-File: LICENSE
Requires-Dist: djangoldp~=4.0
